democritus/__init__.py
democritus/democritus.py
d8s-0.2.0.dist-info/LICENSE
d8s-0.2.0.dist-info/METADATA
d8s-0.2.0.dist-info/WHEEL
d8s-0.2.0.dist-info/top_level.txt
d8s-0.2.0.dist-info/zip-safe
d8s-0.2.0.dist-info/RECORD
